iotronic_ui/__init__.py
iotronic_ui/api/iotronic.py
iotronic_ui/enabled/_6000_iot.py
iotronic_ui/enabled/_6010_iot_boards_panel.py
iotronic_ui/enabled/_6020_iot_plugins_panel.py
iotronic_ui/enabled/_6030_iot_services_panel.py
iotronic_ui/enabled/_6040_iot_webservices_panel.py
iotronic_ui/enabled/_6050_iot_fleets_panel.py
iotronic_ui/iot/__init__.py
iotronic_ui/iot/dashboard.py
iotronic_ui/iot/boards/__init__.py
iotronic_ui/iot/boards/forms.py
iotronic_ui/iot/boards/panel.py
iotronic_ui/iot/boards/tables.py
iotronic_ui/iot/boards/tabs.py
iotronic_ui/iot/boards/tests.py
iotronic_ui/iot/boards/urls.py
iotronic_ui/iot/boards/views.py
iotronic_ui/iot/boards/templates/boards/_attachport.html
iotronic_ui/iot/boards/templates/boards/_cell_services.html
iotronic_ui/iot/boards/templates/boards/_create.html
iotronic_ui/iot/boards/templates/boards/_detachport.html
iotronic_ui/iot/boards/templates/boards/_detail_overview.html
iotronic_ui/iot/boards/templates/boards/_disableservice.html
iotronic_ui/iot/boards/templates/boards/_disablewebservice.html
iotronic_ui/iot/boards/templates/boards/_enableservice.html
iotronic_ui/iot/boards/templates/boards/_enablewebservice.html
iotronic_ui/iot/boards/templates/boards/_removeplugins.html
iotronic_ui/iot/boards/templates/boards/_removeservices.html
iotronic_ui/iot/boards/templates/boards/_update.html
iotronic_ui/iot/boards/templates/boards/attachport.html
iotronic_ui/iot/boards/templates/boards/create.html
iotronic_ui/iot/boards/templates/boards/detachport.html
iotronic_ui/iot/boards/templates/boards/disableservice.html
iotronic_ui/iot/boards/templates/boards/disablewebservice.html
iotronic_ui/iot/boards/templates/boards/enableservice.html
iotronic_ui/iot/boards/templates/boards/enablewebservice.html
iotronic_ui/iot/boards/templates/boards/index.html
iotronic_ui/iot/boards/templates/boards/removeplugins.html
iotronic_ui/iot/boards/templates/boards/removeservices.html
iotronic_ui/iot/boards/templates/boards/update.html
iotronic_ui-0.4.3.dist-info/AUTHORS
iotronic_ui-0.4.3.dist-info/LICENSE
iotronic_ui-0.4.3.dist-info/METADATA
iotronic_ui-0.4.3.dist-info/WHEEL
iotronic_ui-0.4.3.dist-info/pbr.json
iotronic_ui-0.4.3.dist-info/top_level.txt
iotronic_ui-0.4.3.dist-info/RECORD
