Metadata-Version: 2.1
Name: iotronic-ui
Version: 0.4.3
Summary: Iotronic plugin for the OpenStack Dashboard
Home-page: http://www.openstack.org/
Author: OpenStack
Author-email: openstack-dev@lists.openstack.org
License: UNKNOWN
Platform: UNKNOWN
Classifier: Environment :: OpenStack
Classifier: Intended Audience :: Information Technology
Classifier: Intended Audience :: System Administrators
Classifier: License :: OSI Approved :: Apache Software License
Classifier: Operating System :: POSIX :: Linux
Classifier: Programming Language :: Python
Classifier: Programming Language :: Python :: 2
Classifier: Programming Language :: Python :: 2.7
Classifier: Programming Language :: Python :: 3
Classifier: Programming Language :: Python :: 3.5
Requires-Dist: pbr (!=2.1.0,>=2.0.0)
Requires-Dist: Babel (!=2.4.0,>=2.3.4)
Requires-Dist: django-babel (>=0.6.2)
Requires-Dist: django-compressor (>=2.0)
Requires-Dist: django-pyscss (>=2.0.2)
Requires-Dist: Django (<2,>=1.11) ; (python_version<'3.0')
Requires-Dist: Django (<2.1,>=1.11) ; (python_version>='3.0')
